activation_functions/__init__.py
activation_functions/activation_functions.py
activation_functions-0.0.1.dist-info/LICENSE
activation_functions-0.0.1.dist-info/METADATA
activation_functions-0.0.1.dist-info/WHEEL
activation_functions-0.0.1.dist-info/top_level.txt
activation_functions-0.0.1.dist-info/RECORD
